odoo/addons/account_fiscal_position_vies_warning/README.rst
odoo/addons/account_fiscal_position_vies_warning/__init__.py
odoo/addons/account_fiscal_position_vies_warning/__manifest__.py
odoo/addons/account_fiscal_position_vies_warning/i18n/account_fiscal_position_vies_warning.pot
odoo/addons/account_fiscal_position_vies_warning/i18n/es.po
odoo/addons/account_fiscal_position_vies_warning/i18n/it.po
odoo/addons/account_fiscal_position_vies_warning/models/__init__.py
odoo/addons/account_fiscal_position_vies_warning/models/account_fiscal_position.py
odoo/addons/account_fiscal_position_vies_warning/models/account_move.py
odoo/addons/account_fiscal_position_vies_warning/models/res_partner.py
odoo/addons/account_fiscal_position_vies_warning/readme/CONFIGURE.md
odoo/addons/account_fiscal_position_vies_warning/readme/CONTEXT.md
odoo/addons/account_fiscal_position_vies_warning/readme/CONTRIBUTORS.md
odoo/addons/account_fiscal_position_vies_warning/readme/DESCRIPTION.md
odoo/addons/account_fiscal_position_vies_warning/readme/USAGE.md
odoo/addons/account_fiscal_position_vies_warning/static/icon.png
odoo/addons/account_fiscal_position_vies_warning/static/description/icon.png
odoo/addons/account_fiscal_position_vies_warning/static/description/index.html
odoo/addons/account_fiscal_position_vies_warning/tests/__init__.py
odoo/addons/account_fiscal_position_vies_warning/tests/test_fiscal_position_vies_warning.py
odoo/addons/account_fiscal_position_vies_warning/views/account_fiscal_position_view.xml
odoo_addon_account_fiscal_position_vies_warning-18.0.1.0.2.2.dist-info/METADATA
odoo_addon_account_fiscal_position_vies_warning-18.0.1.0.2.2.dist-info/WHEEL
odoo_addon_account_fiscal_position_vies_warning-18.0.1.0.2.2.dist-info/top_level.txt
odoo_addon_account_fiscal_position_vies_warning-18.0.1.0.2.2.dist-info/RECORD
