Metadata-Version: 2.1
Name: odoo-addon-account_fiscal_position_vies_warning
Version: 18.0.1.0.2.2
Requires-Python: >=3.10
Requires-Dist: odoo==18.0.*
Summary: Account Fiscal Position Vies Warning
Home-page: https://github.com/OCA/account-fiscal-rule
License: LGPL-3
Author: Moduon, Odoo Community Association (OCA)
Author-email: support@odoo-community.org
Classifier: Programming Language :: Python
Classifier: Framework :: Odoo
Classifier: Framework :: Odoo :: 18.0
Classifier: License :: OSI Approved :: GNU Lesser General Public License v3 (LGPLv3)
